LICENSE
README.md
setup.py
image_dehazer/__init__.py
image_dehazer.egg-info/PKG-INFO
image_dehazer.egg-info/SOURCES.txt
image_dehazer.egg-info/dependency_links.txt
image_dehazer.egg-info/requires.txt
image_dehazer.egg-info/top_level.txt