Metadata-Version: 2.1
Name: image-dehazer
Version: 0.0.9
Summary: remove haze from images
Home-page: https://github.com/Utkarsh-Deshmukh/Single-Image-Dehazing-Python
Download-URL: https://github.com/Utkarsh-Deshmukh/Single-Image-Dehazing-Python/archive/master.zip
Author: utkarsh-deshmukh
Author-email: utkarsh.deshmukh@gmail.com
License: MIT
Keywords: Single Image Dehazing,Haze Removal
Classifier: Programming Language :: Python :: 3
Classifier: License :: OSI Approved :: MIT License
Classifier: Operating System :: OS Independent
License-File: LICENSE
